nurse_run/__init__.py
nurse_run/__main__.py
nurse_run/run.py
nurse_run-0.1.1.dist-info/LICENSE
nurse_run-0.1.1.dist-info/METADATA
nurse_run-0.1.1.dist-info/WHEEL
nurse_run-0.1.1.dist-info/top_level.txt
nurse_run-0.1.1.dist-info/RECORD
