Metadata-Version: 2.1
Name: nurse-run
Version: 0.1.1
Summary: This package starts and looks after your program, based on the configuration.
Author-email: DDGG <ddcatgg@gmail.com>
License: The MIT License (MIT)        
Project-URL: Homepage, https://github.com/ddcatgg/nurse_run
Project-URL: Bug Tracker, https://github.com/ddcatgg/nurse_run/issues
Keywords: run,tool
Classifier: Programming Language :: Python :: 3
Classifier: License :: OSI Approved :: MIT License
Classifier: Operating System :: OS Independent
Requires-Python: >=3.6
License-File: LICENSE
Requires-Dist: python-dotenv
